setup.py
HTMLProcessor/Grabber.py
HTMLProcessor/__init__.py
SimpleThreading/ThreadPool.py
SimpleThreading/ThreadingByFunction.py
SimpleThreading/__init__.py
ThreadDownloader4834.egg-info/PKG-INFO
ThreadDownloader4834.egg-info/SOURCES.txt
ThreadDownloader4834.egg-info/dependency_links.txt
ThreadDownloader4834.egg-info/top_level.txt